ess_helpers/__init__.py
ess_helpers/arguments.py
ess_helpers/encryption.py
ess_helpers/execute.py
ess_helpers/file_management.py
ess_helpers/exceptions/__init__.py
ess_helpers/exceptions/encryption.py
ess_helpers/exceptions/error_handling.py
ess_helpers/exceptions/execute.py
ess_helpers/exceptions/file_management.py
essential_helpers-0.0.5.dist-info/LICENSE
essential_helpers-0.0.5.dist-info/METADATA
essential_helpers-0.0.5.dist-info/WHEEL
essential_helpers-0.0.5.dist-info/top_level.txt
essential_helpers-0.0.5.dist-info/RECORD
