Metadata-Version: 2.1
Name: essential-helpers
Version: 0.0.5
Summary: Provides basic functions for argument passing, encryption, shell execution and file management
Author-email: jayfalls <j.falls@pm.me>
Project-URL: Homepage, https://github.com/jayfalls/essential-helpers
Project-URL: Issues, https://github.com/jayfalls/essential-helpers/issues
Classifier: Programming Language :: Python :: 3
Classifier: License :: OSI Approved :: MIT License
Classifier: Operating System :: OS Independent
License-File: LICENSE
